dastruct.py
dastruct-0.0.1.dist-info/LICENSE.txt
dastruct-0.0.1.dist-info/METADATA
dastruct-0.0.1.dist-info/WHEEL
dastruct-0.0.1.dist-info/top_level.txt
dastruct-0.0.1.dist-info/RECORD
